matter_persistence/__about__.py
matter_persistence/__init__.py
matter_persistence/decorators.py
matter_persistence/foundation_model.py
matter_persistence/redis/__init__.py
matter_persistence/redis/async_redis_client.py
matter_persistence/redis/base.py
matter_persistence/redis/cache_helper.py
matter_persistence/redis/exceptions.py
matter_persistence/redis/manager.py
matter_persistence/redis/utils.py
matter_persistence/sql/__init__.py
matter_persistence/sql/base.py
matter_persistence/sql/exceptions.py
matter_persistence/sql/manager.py
matter_persistence/sql/utils.py
matter_persistence-1.7.0.dist-info/METADATA
matter_persistence-1.7.0.dist-info/WHEEL
matter_persistence-1.7.0.dist-info/licenses/LICENSE
matter_persistence-1.7.0.dist-info/RECORD
