Metadata-Version: 2.3
Name: matter-persistence
Version: 1.7.0
Summary: Matter persistance library.
Project-URL: Documentation, https://github.com/Matter-Tech/matter-persistence#readme
Project-URL: Issues, https://github.com/Matter-Tech/matter-persistence/issues
Project-URL: Source, https://github.com/Matter-Tech/matter-persistence
Author-email: Rômulo Jales <romulo@thisismatter.com>
License-Expression: MIT
License-File: LICENSE
Keywords: async,orm,pydantic,redis,sql
Classifier: Development Status :: 4 - Beta
Classifier: Programming Language :: Python
Classifier: Programming Language :: Python :: 3.10
Classifier: Programming Language :: Python :: 3.11
Classifier: Programming Language :: Python :: 3.12
Classifier: Programming Language :: Python :: Implementation :: CPython
Classifier: Programming Language :: Python :: Implementation :: PyPy
Requires-Python: >=3.10
Requires-Dist: matter-exceptions~=2.0
Requires-Dist: pydantic~=2.7.0
Requires-Dist: redis~=5.0.3
Requires-Dist: sqlalchemy-utils~=0.41.2
Requires-Dist: sqlalchemy[asyncio]~=2.0.29
Provides-Extra: examples
Requires-Dist: notebook; extra == 'examples'
